ison_parser/__init__.py
ison_parser/py.typed
ison_parser/integrations/__init__.py
ison_parser/integrations/anthropic_integration.py
ison_parser/integrations/autogen_integration.py
ison_parser/integrations/langchain_integration.py
ison_parser/integrations/llamaindex_integration.py
ison_parser/integrations/mcp_client.py
ison_parser/integrations/mcp_server.py
ison_parser/integrations/openai_integration.py
ison_parser/plugins/__init__.py
ison_parser/plugins/chroma_plugin.py
ison_parser/plugins/pinecone_plugin.py
ison_parser/plugins/postgresql_plugin.py
ison_parser/plugins/qdrant_plugin.py
ison_parser/plugins/rudradb_plugin.py
ison_parser/plugins/sqlalchemy_plugin.py
ison_parser/plugins/sqlite_plugin.py
ison_py-1.0.2.dist-info/licenses/LICENSE
ison_py-1.0.2.dist-info/METADATA
ison_py-1.0.2.dist-info/WHEEL
ison_py-1.0.2.dist-info/entry_points.txt
ison_py-1.0.2.dist-info/top_level.txt
ison_py-1.0.2.dist-info/RECORD
