Metadata-Version: 2.4
Name: ison-py
Version: 1.0.2
Summary: ISON (Interchange Simple Object Notation) - A token-efficient data format for AI/LLM workflows
Author: Mahesh Vaikri
Maintainer: Mahesh Vaikri
License: MIT
Project-URL: Homepage, https://www.ison.dev
Project-URL: Documentation, https://www.ison.dev
Project-URL: Repository, https://github.com/maheshvaikri-code/ison
Project-URL: Issues, https://github.com/maheshvaikri-code/ison/issues
Keywords: ison,isonl,json,jsonl,data-format,llm,ai,token-efficient,streaming,fine-tuning,rag,serialization
Classifier: Development Status :: 4 - Beta
Classifier: Intended Audience :: Developers
Classifier: License :: OSI Approved :: MIT License
Classifier: Operating System :: OS Independent
Classifier: Programming Language :: Python :: 3
Classifier: Programming Language :: Python :: 3.9
Classifier: Programming Language :: Python :: 3.10
Classifier: Programming Language :: Python :: 3.11
Classifier: Programming Language :: Python :: 3.12
Classifier: Topic :: Software Development :: Libraries :: Python Modules
Classifier: Topic :: Text Processing :: Markup
Classifier: Topic :: Scientific/Engineering :: Artificial Intelligence
Requires-Python: >=3.9
License-File: LICENSE
Provides-Extra: postgresql
Requires-Dist: psycopg2-binary>=2.9; extra == "postgresql"
Provides-Extra: mysql
Requires-Dist: pymysql>=1.0; extra == "mysql"
Provides-Extra: sqlalchemy
Requires-Dist: sqlalchemy>=2.0; extra == "sqlalchemy"
Provides-Extra: databases
Requires-Dist: psycopg2-binary>=2.9; extra == "databases"
Requires-Dist: pymysql>=1.0; extra == "databases"
Requires-Dist: sqlalchemy>=2.0; extra == "databases"
Provides-Extra: chroma
Requires-Dist: chromadb>=0.4; extra == "chroma"
Provides-Extra: pinecone
Requires-Dist: pinecone-client>=3.0; extra == "pinecone"
Provides-Extra: qdrant
Requires-Dist: qdrant-client>=1.7; extra == "qdrant"
Provides-Extra: vectordbs
Requires-Dist: chromadb>=0.4; extra == "vectordbs"
Requires-Dist: pinecone-client>=3.0; extra == "vectordbs"
Requires-Dist: qdrant-client>=1.7; extra == "vectordbs"
Provides-Extra: all
Requires-Dist: psycopg2-binary>=2.9; extra == "all"
Requires-Dist: pymysql>=1.0; extra == "all"
Requires-Dist: sqlalchemy>=2.0; extra == "all"
Requires-Dist: chromadb>=0.4; extra == "all"
Requires-Dist: pinecone-client>=3.0; extra == "all"
Requires-Dist: qdrant-client>=1.7; extra == "all"
Provides-Extra: dev
Requires-Dist: pytest>=7.0; extra == "dev"
Requires-Dist: pytest-cov>=4.0; extra == "dev"
Requires-Dist: black>=23.0; extra == "dev"
Requires-Dist: isort>=5.0; extra == "dev"
Requires-Dist: mypy>=1.0; extra == "dev"
Dynamic: license-file
